tdsxtract/__about__.py
tdsxtract/__init__.py
tdsxtract/helpers.py
tdsxtract/io.py
tdsxtract/models.py
tdsxtract/optim.py
tdsxtract/stack.py
tdsxtract-0.1.0.dist-info/METADATA
tdsxtract-0.1.0.dist-info/WHEEL
tdsxtract-0.1.0.dist-info/top_level.txt
tdsxtract-0.1.0.dist-info/RECORD
