Metadata-Version: 2.1
Name: tdsxtract
Version: 0.1.0
Summary: Tools for extracting permittivity values from Terahertz Time Domain Spectroscopy measurements.
Home-page: https://tdsxtract.github.io/tdsxtract
Author: Benjamin Vial
Author-email: b.vial@qmul.ac.uk
License: License :: OSI Approved :: MIT License
Project-URL: Documentation, https://tdsxtract.github.io/tdsxtract
Platform: any
Classifier: Development Status :: 1 - Planning
Classifier: License :: OSI Approved :: MIT License
Classifier: Operating System :: OS Independent
Classifier: Programming Language :: Python
Classifier: Programming Language :: Python :: 3
Classifier: Topic :: Scientific/Engineering
Classifier: Topic :: Scientific/Engineering :: Physics
Requires-Dist: numpy
Requires-Dist: scipy
Requires-Dist: matplotlib
Requires-Dist: jax
Requires-Dist: jaxlib
